README.rst
ntr.py
setup.py
ntr.egg-info/PKG-INFO
ntr.egg-info/SOURCES.txt
ntr.egg-info/dependency_links.txt
ntr.egg-info/entry_points.txt
ntr.egg-info/not-zip-safe
ntr.egg-info/requires.txt
ntr.egg-info/top_level.txt