Metadata-Version: 1.0
Name: ntr
Version: 0.0.4
Summary: A Python 3+ CLI application for note.txt notes
Home-page: http://github.com/mrshu/py-ntr
Author: Marek Suppa (mr.Shu)
Author-email: mr@shu.io
License: MIT
Platform: UNKNOWN
